.env.example
01OS/__init__.py
01OS/clients/__init__.py
01OS/clients/base_device.py
01OS/clients/esp32/README.md
01OS/clients/esp32/__init__.py
01OS/clients/esp32/src/client/client.ino
01OS/clients/esp32/websocket_test.py
01OS/clients/mac/__init__.py
01OS/clients/mac/device.py
01OS/clients/rpi/__init__.py
01OS/clients/rpi/device.py
01OS/server/__init__.py
01OS/server/conversations/another-interpreter.json
01OS/server/i.py
01OS/server/llm.py
01OS/server/server.py
01OS/server/services/__init__.py
01OS/server/services/llm/__init__.py
01OS/server/services/llm/litellm/__init__.py
01OS/server/services/llm/litellm/llm.py
01OS/server/services/llm/llamaedge/__init__.py
01OS/server/services/llm/llamaedge/llm.py
01OS/server/services/llm/llamafile/__init__.py
01OS/server/services/llm/llamafile/llm.py
01OS/server/services/stt/__init__.py
01OS/server/services/stt/local-whisper/__init__.py
01OS/server/services/stt/local-whisper/stt.py
01OS/server/services/stt/local-whisper/whisper-rust/.gitignore
01OS/server/services/stt/local-whisper/whisper-rust/Cargo.lock
01OS/server/services/stt/local-whisper/whisper-rust/Cargo.toml
01OS/server/services/stt/local-whisper/whisper-rust/src/main.rs
01OS/server/services/stt/local-whisper/whisper-rust/src/transcribe.rs
01OS/server/services/stt/openai/__init__.py
01OS/server/services/stt/openai/stt.py
01OS/server/services/tts/__init__.py
01OS/server/services/tts/openai/__init__.py
01OS/server/services/tts/openai/tts.py
01OS/server/services/tts/piper/__init__.py
01OS/server/services/tts/piper/tts.py
01OS/server/skills/__init__.py
01OS/server/skills/schedule.py
01OS/server/system_messages/BaseSystemMessage.py
01OS/server/system_messages/TeachModeSystemMessage.py
01OS/server/system_messages/__init__.py
01OS/server/tunnel.py
01OS/server/utils/__init__.py
01OS/server/utils/bytes_to_wav.py
01OS/server/utils/get_system_info.py
01OS/server/utils/kernel.py
01OS/server/utils/logs.py
01OS/server/utils/process_utils.py
01OS/utils/accumulator.py
01os-0.0.13.dist-info/METADATA
01os-0.0.13.dist-info/WHEEL
01os-0.0.13.dist-info/entry_points.txt
01os-0.0.13.dist-info/RECORD
